{
   "statusCode": 200,
   "body": {
      "products": [
         {
            "id": 1,
            "name": "Plant 1",
            "description": "Plant number 1, all the descriptions need improvements, just wait a few hours please",
            "coverImageUrl": "https://media-cdn.tripadvisor.com/media/photo-s/27/9f/45/bc/restaurant.jpg",
            "popular": 0,
            "classification": 1,
            "price": 1.31
         },
         {
            "id": 2,
            "name": "Plant 2",
            "description": "Plant number 2, all the descriptions need improvements, just wait a few hours please",
            "coverImageUrl": "https://static.itdg.com.br/images/auto-auto/447191d9c373e82bada2bccaf2ea21e4/shutterstock-225746563.jpg",
            "popular": 0,
            "classification": 1,
            "price": 2.32
         },
         {
            "id": 3,
            "name": "Plant 3",
            "description": "Plant number 3, all the descriptions need improvements, just wait a few hours please",
            "coverImageUrl": "https://media-cdn.tripadvisor.com/media/photo-s/27/9f/45/bc/restaurant.jpg",
            "popular": 1,
            "classification": 1,
            "price": 3.33
         },
         {
            "id": 4,
            "name": "Plant 4",
            "description": "Plant number 4, all the descriptions need improvements, just wait a few hours please",
            "coverImageUrl": "https://static.itdg.com.br/images/auto-auto/447191d9c373e82bada2bccaf2ea21e4/shutterstock-225746563.jpg",
            "popular": 0,
            "classification": 1,
            "price": 4.34
         },
         {
            "id": 5,
            "name": "Plant 5",
            "description": "Plant number 5, all the descriptions need improvements, just wait a few hours please",
            "coverImageUrl": "https://media-cdn.tripadvisor.com/media/photo-s/27/9f/45/bc/restaurant.jpg",
            "popular": 0,
            "classification": 1,
            "price": 5.35
         },
         {
            "id": 6,
            "name": "Plant 6",
            "description": "Plant number 6, all the descriptions need improvements, just wait a few hours please",
            "coverImageUrl": "https://static.itdg.com.br/images/auto-auto/447191d9c373e82bada2bccaf2ea21e4/shutterstock-225746563.jpg",
            "popular": 0,
            "classification": 1,
            "price": 6.36
         },
         {
            "id": 7,
            "name": "Plant 7",
            "description": "Plant number 7, all the descriptions need improvements, just wait a few hours please",
            "coverImageUrl": "https://media-cdn.tripadvisor.com/media/photo-s/27/9f/45/bc/restaurant.jpg",
            "popular": 1,
            "classification": 1,
            "price": 7.37
         },
         {
            "id": 8,
            "name": "Plant 8",
            "description": "Plant number 8, all the descriptions need improvements, just wait a few hours please",
            "coverImageUrl": "https://static.itdg.com.br/images/auto-auto/447191d9c373e82bada2bccaf2ea21e4/shutterstock-225746563.jpg",
            "popular": 0,
            "classification": 1,
            "price": 8.38
         },
         {
            "id": 9,
            "name": "Plant 9",
            "description": "Plant number 9, all the descriptions need improvements, just wait a few hours please",
            "coverImageUrl": "https://media-cdn.tripadvisor.com/media/photo-s/27/9f/45/bc/restaurant.jpg",
            "popular": 0,
            "classification": 1,
            "price": 9.39
         },
         {
            "id": 10,
            "name": "Plant 10",
            "description": "Plant number 10, all the descriptions need improvements, just wait a few hours please",
            "coverImageUrl": "https://static.itdg.com.br/images/auto-auto/447191d9c373e82bada2bccaf2ea21e4/shutterstock-225746563.jpg",
            "popular": 0,
            "classification": 1,
            "price": 10.40
         },
         {
            "id": 11,
            "name": "Plant 11",
            "description": "Plant number 11, all the descriptions need improvements, just wait a few hours please",
            "coverImageUrl": "https://media-cdn.tripadvisor.com/media/photo-s/27/9f/45/bc/restaurant.jpg",
            "popular": 1,
            "classification": 2,
            "price": 11.41
         },
         {
            "id": 12,
            "name": "Plant 12",
            "description": "Plant number 12, all the descriptions need improvements, just wait a few hours please",
            "coverImageUrl": "https://static.itdg.com.br/images/auto-auto/447191d9c373e82bada2bccaf2ea21e4/shutterstock-225746563.jpg",
            "popular": 0,
            "classification": 2,
            "price": 12.42
         },
         {
            "id": 13,
            "name": "Plant 13",
            "description": "Plant number 13, all the descriptions need improvements, just wait a few hours please",
            "coverImageUrl": "https://media-cdn.tripadvisor.com/media/photo-s/27/9f/45/bc/restaurant.jpg",
            "popular": 0,
            "classification": 2,
            "price": 13.43
         },
         {
            "id": 14,
            "name": "Plant 14",
            "description": "Plant number 14, all the descriptions need improvements, just wait a few hours please",
            "coverImageUrl": "https://static.itdg.com.br/images/auto-auto/447191d9c373e82bada2bccaf2ea21e4/shutterstock-225746563.jpg",
            "popular": 0,
            "classification": 2,
            "price": 14.44
         },
         {
            "id": 15,
            "name": "Plant 15",
            "description": "Plant number 15, all the descriptions need improvements, just wait a few hours please",
            "coverImageUrl": "https://media-cdn.tripadvisor.com/media/photo-s/27/9f/45/bc/restaurant.jpg",
            "popular": 1,
            "classification": 2,
            "price": 15.45
         },
         {
            "id": 16,
            "name": "Plant 16",
            "description": "Plant number 16, all the descriptions need improvements, just wait a few hours please",
            "coverImageUrl": "https://static.itdg.com.br/images/auto-auto/447191d9c373e82bada2bccaf2ea21e4/shutterstock-225746563.jpg",
            "popular": 0,
            "classification": 2,
            "price": 16.46
         },
         {
            "id": 17,
            "name": "Plant 17",
            "description": "Plant number 17, all the descriptions need improvements, just wait a few hours please",
            "coverImageUrl": "https://media-cdn.tripadvisor.com/media/photo-s/27/9f/45/bc/restaurant.jpg",
            "popular": 0,
            "classification": 2,
            "price": 17.47
         },
         {
            "id": 18,
            "name": "Plant 18",
            "description": "Plant number 18, all the descriptions need improvements, just wait a few hours please",
            "coverImageUrl": "https://static.itdg.com.br/images/auto-auto/447191d9c373e82bada2bccaf2ea21e4/shutterstock-225746563.jpg",
            "popular": 0,
            "classification": 2,
            "price": 18.48
         },
         {
            "id": 19,
            "name": "Plant 19",
            "description": "Plant number 19, all the descriptions need improvements, just wait a few hours please.",
            "coverImageUrl": "https://media-cdn.tripadvisor.com/media/photo-s/27/9f/45/bc/restaurant.jpg",
            "popular": 1,
            "classification": 2,
            "price": 19.49
         },
         {
            "id": 20,
            "name": "Plant 20",
            "description": "Plant number 20, all the descriptions need improvements, just wait a few hours please",
            "coverImageUrl": "https://static.itdg.com.br/images/auto-auto/447191d9c373e82bada2bccaf2ea21e4/shutterstock-225746563.jpg",
            "popular": 0,
            "classification": 2,
            "price": 20.50
         }
      ]
   }
}